DeepTricks-2019.9.10.23.5.27.dist-info/METADATA
DeepTricks-2019.9.10.23.5.27.dist-info/RECORD
DeepTricks-2019.9.10.23.5.27.dist-info/WHEEL
DeepTricks-2019.9.10.23.5.27.dist-info/entry_points.txt
DeepTricks-2019.9.10.23.5.27.dist-info/top_level.txt
deeptricks/__init__.py
deeptricks/backend.py
deeptricks/demo.py
deeptricks/files.yml
deeptricks/activations/__init__.py
deeptricks/layers/__init__.py
deeptricks/learn_rate/__init__.py
deeptricks/learn_rate/clr/CyclicLR.py
deeptricks/learn_rate/clr/__init__.py
deeptricks/losses/__init__.py
deeptricks/optimizers/__init__.py
deeptricks/utils/__init__.py
examples/__init__.py
