Metadata-Version: 2.1
Name: DeepTricks
Version: 2019.9.10.23.5.27
Summary: description
Home-page: https://github.com/Jie-Yuan/DeepTricks
Author: JieYuan
Author-email: 313303303@qq.com
Maintainer: JieYuan
Maintainer-email: 313303303@qq.com
License: MIT
Keywords: tool wheel,yuanjie,utils
Platform: all
Classifier: Operating System :: OS Independent
Classifier: Intended Audience :: Developers
Classifier: License :: OSI Approved :: MIT License
Classifier: Programming Language :: Python
Classifier: Programming Language :: Python :: Implementation
Requires-Python: >=3.5
Requires-Dist: tqdm
Requires-Dist: wrapt
